Metadata-Version: 2.1
Name: datamole-anshu-test
Version: 0.1.0
Summary: Dataset versioning and management for ML projects.
Author-email: Anshuman Narayan <anshu.nryn@gmail.com>
License: MIT
Project-URL: Homepage, https://github.com/anshumandec94/datamole
Project-URL: Repository, https://github.com/anshumandec94/datamole
Project-URL: Issues, https://github.com/anshumandec94/datamole/issues
Keywords: data,versioning,ml,datasets,dvc-alternative
Classifier: Development Status :: 3 - Alpha
Classifier: Intended Audience :: Developers
Classifier: Intended Audience :: Science/Research
Classifier: License :: OSI Approved :: MIT License
Classifier: Programming Language :: Python :: 3
Classifier: Programming Language :: Python :: 3.8
Classifier: Programming Language :: Python :: 3.9
Classifier: Programming Language :: Python :: 3.10
Classifier: Programming Language :: Python :: 3.11
Classifier: Topic :: Software Development :: Libraries
Classifier: Topic :: Scientific/Engineering :: Artificial Intelligence
Requires-Python: >=3.8
Requires-Dist: pyyaml>=6.0
Provides-Extra: dev
Requires-Dist: pytest>=7.0; extra == "dev"
Requires-Dist: pytest-cov; extra == "dev"
